testacz/__init__.py
testacz/m_mod_testacz.py
testacz-0.0.1.dist-info/LICENSE.txt
testacz-0.0.1.dist-info/METADATA
testacz-0.0.1.dist-info/WHEEL
testacz-0.0.1.dist-info/top_level.txt
testacz-0.0.1.dist-info/RECORD
