Metadata-Version: 2.1
Name: testacz
Version: 0.0.1
Summary: My first test package
Author-email: ACZ <adrian.cze96@hotmail.com>
License: MIT License
Keywords: testacz,name,three elements
Classifier: Framework :: IDLE
Classifier: Natural Language :: Polish
Requires-Python: >=3.0
License-File: LICENSE.txt
Requires-Dist: python-version (>='3.0')
Requires-Dist: numpy
